{
  "questions": [
    {
      "question": "신조어 '댕댕이'의 의미는?",
      "choices": [
        "볼이 통통한 어린아이",
        "애교가 넘치는 애인",
        "강아지"
      ],
      "answer": "2",
      "explain": "댕댕이 = 멍멍이 글자 모양이 비슷해서 지어진 신조어."
    },
    {
      "question": "사람의 신체 장기 중, 개수가 2개인 것은?",
      "choices": [
        "심장",
        "신장",
        "간"
      ],
      "answer": "1",
      "explain": ""
    },
    {
      "question": "점심은 어떻게 먹는 것을 뜻할까요?",
      "choices": [
        "점점 배불리 먹음",
        "마음에 점을 찍듯 조금 먹음",
        "점점 반찬 수를 늘려가며 먹음"
      ],
      "answer": "1",
      "explain": ""
    },
    {
      "question": "우리 나라 최초의 TV 시리즈용 국산 애니메이션은?",
      "choices": [
        "두치와 뿌꾸",
        "달려라 하니",
        "날아라 슈퍼보드"
      ],
      "answer": "1",
      "explain": "두치와 뿌꾸 - 1988년 달려라 하니 - 1990년 날아라 슈퍼보드 - 1996년 두치와 뿌꾸가 제작년도가 더 빠르나 TV 시리즈용은 달려라 하니가 국내 최초이다."
    },
    {
      "question": "우리나라 국보 1호는 무엇일까요?",
      "choices": [
        "숭례문",
        "경복궁",
        "보신각종"
      ],
      "answer": "0",
      "explain": ""
    },
    {
      "question": "비행기 이착륙 시 창문 덮개를 여는 이유?",
      "choices": [
        "창문 열고 닫는 것이 잘 되는 지 확인하려고",
        "비행기 안팎의 이상 여부를 확인하려고",
        "건조한 기내의 습도를 높이려고"
      ],
      "answer": "1",
      "explain": "비행기 동체나 엔진에 문제가 있는지 예상 착륙 장소에 제대로 착륙 중인지 등을 확인하기 위해 비행기 창문 덮개를 연다."
    },
    {
      "question": "그래미상에서 그래미는 어떤 단어에서 유래했을까요?",
      "choices": [
        "축음기",
        "LP판",
        "마이크"
      ],
      "answer": "0",
      "explain": "축음기를 의미하는 그라모폰(Gramophone)에서 유래."
    },
    {
      "question": "다음 중 성별이 다른 작가는 누구일까요?",
      "choices": [
        "김유정",
        "박경리",
        "김소월"
      ],
      "answer": "1",
      "explain": ""
    },
    {
      "question": "'자신의 운명을 받아들이고 사랑하라'는 뜻의 이 말은 무엇일까요?",
      "choices": [
        "카르페디엠",
        "나르시시즘",
        "아모르파티"
      ],
      "answer": "2",
      "explain": "카르페디엠 - 오늘을 즐겨라, 나르시시즘 - 자기애 자아도취"
    },
    {
      "question": "대학교에서 8월에 하는 졸업식을 () 졸업식이라고 하는데요. ()은?",
      "choices": [
        "국화",
        "억새",
        "코스모스"
      ],
      "answer": "2",
      "explain": ""
    },
    {
      "question": "홍길동전의 저자는 누구일까요?",
      "choices": [
        "허난설헌",
        "허균",
        "허봉"
      ],
      "answer": "1",
      "explain": ""
    },
    {
      "question": "현금 자동 인출기(ATM)에서 M은 무엇을 뜻할까요?",
      "choices": [
        "머니(Money)",
        "머신(Machine)",
        "메뉴얼(Manual)"
      ],
      "answer": "1",
      "explain": ""
    },
    {
      "question": "우리 나라에서 최초로 발명한 것이 아닌 것은?",
      "choices": [
        "커피믹스",
        "와이파이",
        "이태리 타올"
      ],
      "answer": "1",
      "explain": "와이파이는 1940년에 오스트리아 공학자가 개발했다."
    },
    {
      "question": "가장 통증 지수가 높은 부위는 어디일까요?",
      "choices": [
        "콧구멍",
        "손바닥",
        "겨드랑이"
      ],
      "answer": "0",
      "explain": ""
    },
    {
      "question": "맹자의 사단설에서 남을 불상히 여기는 마음을 뜻하는 말은?",
      "choices": [
        "측은지심",
        "수오지심",
        "사양지심"
      ],
      "answer": "0",
      "explain": "수오지심 -  옳지 못함을 부끄러워하고 착하지 못함을 미워하는 마음을 이른다., 사양지심 -  겸손히 남에게 사양하는 마음을 이른다."
    },
    {
      "question": "낙지의 다리 수와 같은 해산물은?",
      "choices": [
        "문어",
        "꼴뚜기",
        "오징어"
      ],
      "answer": "0",
      "explain": "꼴뚜기 - 8개, 오징어 10개"
    },
    {
      "question": "최초로 주민등록증을 발급받은 캐릭터는 누구일까요?",
      "choices": [
        "뽀로로",
        "둘리",
        "콩순이"
      ],
      "answer": "1",
      "explain": ""
    },
    {
      "question": "독립 선언서 낭독이 이뤄진, 서울 최초의 근대식 공원은?",
      "choices": [
        "탑골공원",
        "낙산공원",
        "효창공원"
      ],
      "answer": "0",
      "explain": ""
    },
    {
      "question": "다음 중 손의 방향이 다른 건 무엇일가요?",
      "choices": [
        "뉴욕 '자유의 여신상'에서 횃불을 쥔 손",
        "로댕의 '생각하는 사람'에서 괴고 있는 손",
        "광화문의 '세종대왕 동상'에서 책을 든 손"
      ],
      "answer": "2",
      "explain": ""
    },
    {
      "question": "OST는 무엇의 약자일까요?",
      "choices": [
        "오케스트라 사운드 트랙(Orchestra Sound Track)",
        "오페라 사운드 트랙(Opera Sound Track)",
        "오리지널 사운드 트랙(Original Sound Track)"
      ],
      "answer": "2",
      "explain": ""
    },
    {
      "question": "공휴일이 아닌 날은 언제일까요?",
      "choices": [
        "개천절",
        "제헌절",
        "한글날"
      ],
      "answer": "1",
      "explain": ""
    },
    {
      "question": "2019년 최저 임금은 얼마일까요?",
      "choices": [
        "7530원",
        "8350원",
        "9350원"
      ],
      "answer": "1",
      "explain": ""
    },
    {
      "question": "프랑스 작가 빅토르 위고의 장편소설 '레미제라블'의 주인공인 장발장이 출소 후 성당에서 훔친 것은?",
      "choices": [
        "은접시",
        "금시계",
        "땅문서"
      ],
      "answer": "0",
      "explain": ""
    },
    {
      "question": "독일의 철학자 괴테는 자신의 삶을 세 단어로 표현했다. '사랑노라, 괴로워했노라, 그리고 ( )이라'고 했는데요. 무엇일까요?",
      "choices": [
        "후회했노라",
        "배웠노라",
        "잊었노라"
      ],
      "answer": "1",
      "explain": ""
    },
    {
      "question": "'미꾸라지를 운송할 때 이 물고기를 넣으면 미꾸라지들이 그것을 피해 다니느라 생기를 얻어 죽지 않는다'는 설에 비롯한 이 이론을 무엇이라고 할까요?",
      "choices": [
        "뱀장어 효과",
        "대구 효과",
        "메기 효과"
      ],
      "answer": "2",
      "explain": ""
    },
    {
      "question": "'회자되다'에서 회는 무슨 뜻일까요?",
      "choices": [
        "날고기",
        "생각하다",
        "다시"
      ],
      "answer": "0",
      "explain": "회자-회 회(膾)+구운 고기 자(炙)회와 구운 고기에서 나온 말이다"
    }
  ]
}
